{
  "config": {
      "step": {
        "user": {
          "data": {
            "personal_id": "Personal ID number",
            "pin_code": "ICA PIN code",
            "recipe_count": "Number of random recipes"
          },
          "data_description":
          {
            "personal_id": "10 digits, no hyphen",
            "pin_code": "4-6 numbers, used to be found at the back of your ICA Buffe magazine",
            "recipe_count": "0 deactivates"
          }
        }
      },
      "error": {
        "cannot_connect": "[%key:common::config_flow::error::cannot_connect%]",
        "invalid_credentials": "[%key:common::config_flow::error::invalid_credentials%]",
        "unknown": "[%key:common::config_flow::error::unknown%]"
      },
      "abort": {
        "single_instance_allowed": "[%key:common::config_flow::abort::single_instance_allowed%]"
      },
      "create_entry": {
        "default": "[%key:common::config_flow::create_entry::authenticated%]"
      }
    }
  }